setup.py
sample_space/__init__.py
sample_space/lambdas.py
sample_space/rvs.py
sample_space/sample_space.py
sample_space.egg-info/PKG-INFO
sample_space.egg-info/SOURCES.txt
sample_space.egg-info/dependency_links.txt
sample_space.egg-info/not-zip-safe
sample_space.egg-info/requires.txt
sample_space.egg-info/top_level.txt