Metadata-Version: 1.0
Name: sample-space
Version: 0.2.0
Summary: A simple API for defining sample spaces (to run simple statistical simulations)
Home-page: http://github.com/asross/sample_space
Author: Andrew Ross
Author-email: andrewslavinross@gmail.com
License: MIT
Platform: UNKNOWN
